README.md
setup.py
Docker/Dockerfile
Docker/theonionbox.cfg
FreeBSD/theonionbox.sh
docs/description.rst
docs/images/bandwidth.png
docs/images/cc.png
docs/images/configuration.png
docs/images/connectionerror.png
docs/images/control.png
docs/images/generalinfo.png
docs/images/header.png
docs/images/hidden.png
docs/images/local.png
docs/images/location.png
docs/images/login.png
docs/images/messages.png
docs/images/network.png
docs/images/pclogo.svg
docs/images/raspbian.png
docs/images/weights.png
init.d/theonionbox.sh
systemd/theonionbox.service
theonionbox/__init__.py
theonionbox/__main__.py
theonionbox/stamp.py
theonionbox/theonionbox.py
theonionbox.egg-info/PKG-INFO
theonionbox.egg-info/SOURCES.txt
theonionbox.egg-info/dependency_links.txt
theonionbox.egg-info/entry_points.txt
theonionbox.egg-info/requires.txt
theonionbox.egg-info/top_level.txt
theonionbox/config/theonionbox.example
theonionbox/css/box.css
theonionbox/css/cc.css
theonionbox/libs/LatoLatin/OFL.txt
theonionbox/libs/LatoLatin/README-WEB.txt
theonionbox/libs/LatoLatin/latolatinfonts.css
theonionbox/libs/LatoLatin/fonts/LatoLatin-Black.eot
theonionbox/libs/LatoLatin/fonts/LatoLatin-Black.ttf
theonionbox/libs/LatoLatin/fonts/LatoLatin-Black.woff
theonionbox/libs/LatoLatin/fonts/LatoLatin-Black.woff2
theonionbox/libs/LatoLatin/fonts/LatoLatin-BlackItalic.eot
theonionbox/libs/LatoLatin/fonts/LatoLatin-BlackItalic.ttf
theonionbox/libs/LatoLatin/fonts/LatoLatin-BlackItalic.woff
theonionbox/libs/LatoLatin/fonts/LatoLatin-BlackItalic.woff2
theonionbox/libs/LatoLatin/fonts/LatoLatin-Bold.eot
theonionbox/libs/LatoLatin/fonts/LatoLatin-Bold.ttf
theonionbox/libs/LatoLatin/fonts/LatoLatin-Bold.woff
theonionbox/libs/LatoLatin/fonts/LatoLatin-Bold.woff2
theonionbox/libs/LatoLatin/fonts/LatoLatin-BoldItalic.eot
theonionbox/libs/LatoLatin/fonts/LatoLatin-BoldItalic.ttf
theonionbox/libs/LatoLatin/fonts/LatoLatin-BoldItalic.woff
theonionbox/libs/LatoLatin/fonts/LatoLatin-BoldItalic.woff2
theonionbox/libs/LatoLatin/fonts/LatoLatin-Hairline.eot
theonionbox/libs/LatoLatin/fonts/LatoLatin-Hairline.ttf
theonionbox/libs/LatoLatin/fonts/LatoLatin-Hairline.woff
theonionbox/libs/LatoLatin/fonts/LatoLatin-Hairline.woff2
